flash_patcher/__main__.py
flash_patcher/patcher.py
flash_patcher/antlr/PatchfileLexer.g4
flash_patcher/antlr/PatchfileParser.g4
flash_patcher/antlr_source/.gitkeep
flash_patcher/compile/compilation.py
flash_patcher/compile/ffdec.py
flash_patcher/compile/locate_decomp.py
flash_patcher/exception/dependency.py
flash_patcher/exception/error_manager.py
flash_patcher/exception/error_suppression.py
flash_patcher/exception/injection.py
flash_patcher/inject/bulk_injection.py
flash_patcher/inject/find_content.py
flash_patcher/inject/single_injection.py
flash_patcher/inject/location/constant_injection_location.py
flash_patcher/inject/location/injection_location.py
flash_patcher/inject/location/parser_injection_location.py
flash_patcher/parse/common.py
flash_patcher/parse/patch.py
flash_patcher/parse/patch_visitor.py
flash_patcher/parse/scope.py
flash_patcher/util/external_cmd.py
flash_patcher/util/file_copy.py
flash_patcher/util/file_io.py
flash_patcher/util/logging.py
flash_patcher/antlr_source/.gitkeep
flash_patcher/antlr_source/PatchfileLexer.g4
flash_patcher/antlr_source/PatchfileLexer.interp
flash_patcher/antlr_source/PatchfileLexer.py
flash_patcher/antlr_source/PatchfileLexer.tokens
flash_patcher/antlr_source/PatchfileParser.g4
flash_patcher/antlr_source/PatchfileParser.interp
flash_patcher/antlr_source/PatchfileParser.py
flash_patcher/antlr_source/PatchfileParser.tokens
flash_patcher/antlr_source/PatchfileParserListener.py
flash_patcher/antlr_source/PatchfileParserVisitor.py
flash_patcher/antlr_source/__init__.py
flash_patcher-6.3.0.dist-info/METADATA
flash_patcher-6.3.0.dist-info/WHEEL
flash_patcher-6.3.0.dist-info/entry_points.txt
flash_patcher-6.3.0.dist-info/RECORD
