Metadata-Version: 2.3
Name: flash-patcher
Version: 6.3.0
Summary: rayyaw's SWF patcher
Project-URL: Documentation, https://github.com/rayyaw/flash-patcher
Project-URL: Source, https://github.com/rayyaw/flash-patcher
Project-URL: History, https://github.com/rayyaw/flash-patcher
Project-URL: Issues, https://github.com/rayyaw/flash-patcher/issues
Author-email: rayyaw <rayyawspeedruns@gmail.com>, qtkito <gtcreyon@gmail.com>, GTcreyon <gtcreyon@gmail.com>
License:                     GNU AFFERO GENERAL PUBLIC LICENSE
Keywords: flash,patcher
Classifier: Development Status :: 5 - Production/Stable
Classifier: Environment :: Console
Classifier: Intended Audience :: Developers
Classifier: License :: Free To Use But Restricted
Classifier: Operating System :: OS Independent
Classifier: Programming Language :: Python
Classifier: Programming Language :: Python :: 3
Classifier: Programming Language :: Python :: 3 :: Only
Classifier: Programming Language :: Python :: 3.10
Classifier: Programming Language :: Python :: 3.11
Classifier: Programming Language :: Python :: 3.12
Classifier: Topic :: Software Development :: Build Tools
Classifier: Topic :: Software Development :: Compilers
Requires-Python: >=3.10
Requires-Dist: antlr4-python3-runtime>=4.7.0
